[{"model": "authapp.user", "pk": 1, "fields": {"password": "pbkdf2_sha256$216000$WOjSZUB9hkKq$7IuuoyKIdgS4t0jBqagozf9zMd7qo+kYMpUmSO7uJkI=", "last_login": "2021-02-27T09:19:06.771Z", "is_superuser": true, "first_name": "", "last_name": "", "is_staff": true, "is_active": true, "date_joined": "2021-01-29T18:38:33.835Z", "username": "user", "name": "Maxim", "surname": "Baranov", "status_block": false, "status_update": "2021-01-29T18:38:33.835Z", "date_create": "2021-01-29T18:38:33.835Z", "date_update": "2021-01-29T18:38:33.835Z", "email": "maxis-ea@narod.ru", "avatar": "users_avatars/34841853.jpeg", "age": 99999, "aboutMe": "Я пришел к тебе с дискетой,\r\nРассказать, что сеть упала,\r\nЯ летел к тебе кометой,\r\nЧто бы ты все это знала.\r\nСеть проверю досконально\r\nИ обрыв найду я срочно,\r\nЗапаяю капитально - \r\nЗнаю алгоритм я точно!\r\nЯ надежный твой хранитель,\r\nЯ - админ сети общажной\r\nЯ он-лайновый воитель\r\nЧеловек я очень важный!\r\nВ общем, знай, обычный ламер,\r\nЯ и занят и загружен,\r\nЭто ты невинный гамер,\r\nЯ ж по жизни - очень нужен!", "groups": [], "user_permissions": []}}, {"model": "authapp.user", "pk": 2, "fields": {"password": "pbkdf2_sha256$216000$9uzAlsOJrbUR$xmSnwo5kShAg+6fCCWn0RIaYjpjCNtIKgpqAgJnx45c=", "last_login": "2021-02-27T11:09:21.002Z", "is_superuser": false, "first_name": "", "last_name": "", "is_staff": false, "is_active": true, "date_joined": "2021-01-29T18:39:28.852Z", "username": "reanimator", "name": "Mikhail", "surname": "Ageev", "status_block": false, "status_update": "2021-01-29T18:39:28.852Z", "date_create": "2021-01-29T18:39:28.852Z", "date_update": "2021-01-29T18:39:28.852Z", "email": "ageev.mikhail.23@gmail.com", "avatar": "users_avatars/Small_IMG_7053.jpg", "age": 36, "aboutMe": "", "groups": [1], "user_permissions": []}}, {"model": "authapp.user", "pk": 3, "fields": {"password": "pbkdf2_sha256$216000$OO58DHcWgLlv$vwc9yijtarrz3eZ+qyD0HOCy0Ii1aAyOiA0hI+SsI5k=", "last_login": "2021-02-15T02:58:42.866Z", "is_superuser": false, "first_name": "", "last_name": "", "is_staff": false, "is_active": true, "date_joined": "2021-01-29T18:40:38.418Z", "username": "agile", "name": "Аджаил Джуниор", "surname": "Аджаилов Оглы", "status_block": false, "status_update": "2021-01-29T18:40:38.418Z", "date_create": "2021-01-29T18:40:38.418Z", "date_update": "2021-01-29T18:40:38.418Z", "email": "agile@gmail.com", "avatar": "", "age": 0, "aboutMe": "", "groups": [1], "user_permissions": []}}, {"model": "authapp.user", "pk": 4, "fields": {"password": "pbkdf2_sha256$216000$6CUXOpYW4P0p$7a/2N99NDWFnDZxSbPhsZihGI4lBZVHfTWQ88FX/fmU=", "last_login": "2021-02-01T14:51:08.684Z", "is_superuser": false, "first_name": "", "last_name": "", "is_staff": false, "is_active": true, "date_joined": "2021-02-01T14:50:21.272Z", "username": "vasy", "name": "vasy", "surname": "vasylievskij Ogly", "status_block": false, "status_update": "2021-02-01T15:50:21.272Z", "date_create": "2021-02-01T15:50:21.272Z", "date_update": "2021-02-01T15:50:21.272Z", "email": "vasy@gmail.com", "avatar": "", "age": 0, "aboutMe": "", "groups": [], "user_permissions": []}}, {"model": "authapp.user", "pk": 5, "fields": {"password": "pbkdf2_sha256$216000$3Ewyo0OpTrhZ$JGnqmUHrX8FKdaRorK642bEpl96tcoH8/xFrAYgE5h8=", "last_login": "2021-02-09T17:01:44.953Z", "is_superuser": false, "first_name": "", "last_name": "", "is_staff": false, "is_active": true, "date_joined": "2021-02-02T15:06:19.310Z", "username": "justdust", "name": "София", "surname": "Мирошниченко", "status_block": false, "status_update": "2021-02-02T15:06:19.310Z", "date_create": "2021-02-02T15:06:19.310Z", "date_update": "2021-02-02T15:06:19.310Z", "email": "2@d.ru", "avatar": "", "age": 0, "aboutMe": "", "groups": [1], "user_permissions": []}}, {"model": "authapp.user", "pk": 6, "fields": {"password": "pbkdf2_sha256$216000$hXRqLIdxv9cX$B7L5jrj51IKpZHfUTHA6NCBrpAP1Ngo39xu5B88yi3w=", "last_login": "2021-02-08T06:08:16.767Z", "is_superuser": false, "first_name": "", "last_name": "", "is_staff": false, "is_active": true, "date_joined": "2021-02-05T19:52:24.364Z", "username": "Ximaxis", "name": "Alex", "surname": "Korolev", "status_block": false, "status_update": "2021-02-05T19:52:24.364Z", "date_create": "2021-02-05T19:52:24.364Z", "date_update": "2021-02-05T19:52:24.364Z", "email": "maxis-ea1@ya.ru", "avatar": "", "age": 0, "aboutMe": "", "groups": [1], "user_permissions": []}}, {"model": "authapp.user", "pk": 7, "fields": {"password": "pbkdf2_sha256$216000$XMTI38KE4YjS$D8cWrMerOgUzZRTITZbgYwEiq3m4pnxP70Q6OT2ft/8=", "last_login": "2021-02-05T19:58:52.790Z", "is_superuser": false, "first_name": "", "last_name": "", "is_staff": false, "is_active": true, "date_joined": "2021-02-05T19:56:15.930Z", "username": "valera", "name": "Mikhail", "surname": "Ageev", "status_block": false, "status_update": "2021-02-05T19:56:15.930Z", "date_create": "2021-02-05T19:56:15.930Z", "date_update": "2021-02-05T19:56:15.930Z", "email": "valera@gmail.com", "avatar": "", "age": 0, "aboutMe": "", "groups": [], "user_permissions": []}}, {"model": "authapp.user", "pk": 8, "fields": {"password": "pbkdf2_sha256$216000$ma5B8Fn0Pqha$PVRYOLNwZlLT8gY5hgiBJKbvsyvuGrGADpdSkq/+am8=", "last_login": null, "is_superuser": false, "first_name": "", "last_name": "", "is_staff": false, "is_active": true, "date_joined": "2021-02-05T19:56:40.561Z", "username": "Druid", "name": "Еще_один", "surname": "Юзер", "status_block": false, "status_update": "2021-02-05T19:56:40.561Z", "date_create": "2021-02-05T19:56:40.561Z", "date_update": "2021-02-05T19:56:40.561Z", "email": "maxis-ea2@ya.ru", "avatar": "", "age": 0, "aboutMe": "", "groups": [], "user_permissions": []}}, {"model": "authapp.user", "pk": 9, "fields": {"password": "pbkdf2_sha256$216000$Y1JEN3C0FwTO$ZzFFgoyz1qC6ARk/Ov/SCFlKyikNFNTPnlr1CAwQBzU=", "last_login": "2021-02-05T20:03:30.830Z", "is_superuser": false, "first_name": "", "last_name": "", "is_staff": false, "is_active": true, "date_joined": "2021-02-05T20:02:45.060Z", "username": "leopold", "name": "leopold", "surname": "leopoldovich", "status_block": false, "status_update": "2021-02-05T20:02:45.060Z", "date_create": "2021-02-05T20:02:45.060Z", "date_update": "2021-02-05T20:02:45.060Z", "email": "leopold@gmail.com", "avatar": "", "age": 0, "aboutMe": "", "groups": [], "user_permissions": []}}, {"model": "authapp.user", "pk": 10, "fields": {"password": "pbkdf2_sha256$216000$Iw6QrKO02o1V$4SIYfiLcnjexpj2LYd4nOqZKkLiUP6SPqciJinAJcN4=", "last_login": "2021-02-06T11:21:08.351Z", "is_superuser": false, "first_name": "", "last_name": "", "is_staff": false, "is_active": true, "date_joined": "2021-02-06T11:20:55.592Z", "username": "fghjk", "name": "fghjk", "surname": "12345", "status_block": false, "status_update": "2021-02-06T11:20:55.592Z", "date_create": "2021-02-06T11:20:55.593Z", "date_update": "2021-02-06T11:20:55.593Z", "email": "Vasia@gmail.com", "avatar": "", "age": 0, "aboutMe": "", "groups": [], "user_permissions": []}}, {"model": "authapp.user", "pk": 11, "fields": {"password": "pbkdf2_sha256$216000$EmpRv6cJMxei$S8D2N0AJ0Pv9BJYJjHASdO5wToGsLXyv8mCuIlWQd8g=", "last_login": "2021-02-07T00:33:18.991Z", "is_superuser": false, "first_name": "", "last_name": "", "is_staff": false, "is_active": true, "date_joined": "2021-02-06T17:17:22.585Z", "username": "romeo", "name": "Romeo", "surname": "Montecchi", "status_block": false, "status_update": "2021-02-06T17:17:22.585Z", "date_create": "2021-02-06T17:17:22.585Z", "date_update": "2021-02-06T17:17:22.585Z", "email": "romeo@freelove.com", "avatar": "", "age": 0, "aboutMe": "", "groups": [], "user_permissions": []}}, {"model": "authapp.user", "pk": 12, "fields": {"password": "pbkdf2_sha256$216000$wfQXSyyOIzyZ$0Zv2eNpYDLd47mH1+HTouUoAvleglIS2CJDtGkbl4lg=", "last_login": "2021-02-09T21:54:23.644Z", "is_superuser": false, "first_name": "", "last_name": "", "is_staff": false, "is_active": true, "date_joined": "2021-02-07T22:08:19.866Z", "username": "anna", "name": "Анна", "surname": "Романова", "status_block": false, "status_update": "2021-02-07T22:08:19.866Z", "date_create": "2021-02-07T22:08:19.866Z", "date_update": "2021-02-07T22:08:19.866Z", "email": "jhg@love.com", "avatar": "", "age": 0, "aboutMe": "", "groups": [], "user_permissions": []}}, {"model": "authapp.user", "pk": 13, "fields": {"password": "pbkdf2_sha256$216000$28tt0oNNmSGL$aKK2XiOPB6On9JomyHg8cz1qm0OKFMVO5+pUe2AU0vo=", "last_login": "2021-02-10T15:37:29.388Z", "is_superuser": false, "first_name": "", "last_name": "", "is_staff": false, "is_active": true, "date_joined": "2021-02-10T15:37:27.691Z", "username": "user2", "name": "user", "surname": "vasia", "status_block": false, "status_update": "2021-02-10T16:37:27.691Z", "date_create": "2021-02-10T16:37:27.691Z", "date_update": "2021-02-10T16:37:27.691Z", "email": "user2@gmail.com", "avatar": "", "age": 0, "aboutMe": "", "groups": [], "user_permissions": []}}, {"model": "authapp.user", "pk": 14, "fields": {"password": "pbkdf2_sha256$216000$lRJqxH7EwHeS$AXlz/6oLcqj7EDMGj+ySC89XV+Y7LGo2n6Jm5YXfbOU=", "last_login": "2021-02-26T22:55:02.852Z", "is_superuser": false, "first_name": "", "last_name": "", "is_staff": false, "is_active": true, "date_joined": "2021-02-11T03:13:36.362Z", "username": "kindle", "name": "Иозеф", "surname": "Швейк", "status_block": false, "status_update": "2021-02-11T03:13:36.362Z", "date_create": "2021-02-11T03:13:36.362Z", "date_update": "2021-02-11T03:13:36.362Z", "email": "schweik@gmail.com", "avatar": "users_avatars/schweik.jpeg", "age": 45, "aboutMe": "Швейк. Просто Швейк.", "groups": [], "user_permissions": []}}, {"model": "authapp.user", "pk": 15, "fields": {"password": "pbkdf2_sha256$216000$c1wb5n8B28k8$mg9LCeEL/6oXK6AjkGfuBgYz5Y9DuUVRpP3MSBm4B4s=", "last_login": "2021-02-16T04:48:07.007Z", "is_superuser": false, "first_name": "", "last_name": "", "is_staff": false, "is_active": true, "date_joined": "2021-02-12T18:04:52.645Z", "username": "user3", "name": "user3", "surname": "user3", "status_block": false, "status_update": "2021-02-12T18:04:52.645Z", "date_create": "2021-02-12T18:04:52.645Z", "date_update": "2021-02-12T18:04:52.645Z", "email": "maxis-ea@yandex.ru", "avatar": "", "age": 0, "aboutMe": "", "groups": [], "user_permissions": []}}, {"model": "authapp.user", "pk": 16, "fields": {"password": "pbkdf2_sha256$216000$R37M4EK5O53Y$gVvD4i8gCefRnfw/CyTW5M87W1ghBtcvJXU3iZgCPNs=", "last_login": "2021-02-12T18:04:57.708Z", "is_superuser": false, "first_name": "", "last_name": "", "is_staff": false, "is_active": true, "date_joined": "2021-02-12T18:04:55.923Z", "username": "user8", "name": "user8", "surname": "vasia", "status_block": false, "status_update": "2021-02-12T19:04:55.923Z", "date_create": "2021-02-12T19:04:55.923Z", "date_update": "2021-02-12T19:04:55.923Z", "email": "user8@gmail.com", "avatar": "", "age": 0, "aboutMe": "", "groups": [], "user_permissions": []}}, {"model": "authapp.user", "pk": 17, "fields": {"password": "pbkdf2_sha256$216000$CxLrd1k66ojX$2Y1RhmTKZ79LUyvdPNbaT9fYkYMfx10R4lPl30D25gY=", "last_login": "2021-02-12T18:04:57.890Z", "is_superuser": false, "first_name": "", "last_name": "", "is_staff": false, "is_active": true, "date_joined": "2021-02-12T18:04:57.557Z", "username": "justdust1", "name": "София", "surname": "Мирошниченко", "status_block": false, "status_update": "2021-02-12T18:04:57.557Z", "date_create": "2021-02-12T18:04:57.557Z", "date_update": "2021-02-12T18:04:57.557Z", "email": "justdust1@ya.ru", "avatar": "", "age": 0, "aboutMe": "", "groups": [], "user_permissions": []}}, {"model": "authapp.user", "pk": 18, "fields": {"password": "pbkdf2_sha256$216000$gPuwk0TwHBME$ncLn1yWPtu192Y6jtLR4IF6E+qhyZ7yWQZgZGS93KXo=", "last_login": "2021-02-13T10:12:40.383Z", "is_superuser": false, "first_name": "", "last_name": "", "is_staff": false, "is_active": true, "date_joined": "2021-02-13T10:12:40.038Z", "username": "user222", "name": "София", "surname": "Мирошниченко", "status_block": false, "status_update": "2021-02-13T10:12:40.038Z", "date_create": "2021-02-13T10:12:40.038Z", "date_update": "2021-02-13T10:12:40.038Z", "email": "miroshnichenkosonechka@yandex.ry", "avatar": "", "age": 0, "aboutMe": "", "groups": [], "user_permissions": []}}, {"model": "authapp.user", "pk": 19, "fields": {"password": "pbkdf2_sha256$216000$BnAEjGrE2Jz2$D/KnpCsz6YLZZdE69oEp0aAqhNz4KlnPu8CP5nhyF0Q=", "last_login": "2021-02-14T19:58:09.308Z", "is_superuser": false, "first_name": "", "last_name": "", "is_staff": false, "is_active": true, "date_joined": "2021-02-13T16:55:52.073Z", "username": "olesiavolodina", "name": "олеся", "surname": "volodina", "status_block": false, "status_update": "2021-02-13T16:55:52.073Z", "date_create": "2021-02-13T16:55:52.073Z", "date_update": "2021-02-13T16:55:52.073Z", "email": "olesia_volodina@mail.ru", "avatar": "", "age": 0, "aboutMe": "", "groups": [], "user_permissions": []}}, {"model": "authapp.user", "pk": 20, "fields": {"password": "pbkdf2_sha256$216000$jby4cxeBVz78$e3kYBl4KCUmYABWMoczBHVZiUZysPmfVgcTPod0NIBY=", "last_login": "2021-02-27T11:05:52.760Z", "is_superuser": false, "first_name": "", "last_name": "", "is_staff": false, "is_active": true, "date_joined": "2021-02-13T17:00:41.081Z", "username": "oleg.gnome", "name": "Oleg", "surname": "Maslov", "status_block": false, "status_update": "2021-02-13T17:00:41.081Z", "date_create": "2021-02-13T17:00:41.081Z", "date_update": "2021-02-13T17:00:41.081Z", "email": "oleg.gnome@yandex.ru", "avatar": "", "age": 0, "aboutMe": "", "groups": [], "user_permissions": []}}, {"model": "authapp.user", "pk": 21, "fields": {"password": "pbkdf2_sha256$216000$iiqjrZGyfXE1$rD3RSMxyOwCA3VSSKNR/FEyS58SaTz9+GqjDwrQT4no=", "last_login": null, "is_superuser": false, "first_name": "", "last_name": "", "is_staff": false, "is_active": false, "date_joined": "2021-02-14T03:05:45.030Z", "username": "emailuser", "name": "Прохор", "surname": "Шмидт", "status_block": false, "status_update": "2021-02-14T03:05:45.030Z", "date_create": "2021-02-14T03:05:45.030Z", "date_update": "2021-02-14T03:05:45.030Z", "email": "kirikeza@gmail.com", "avatar": "", "age": 0, "aboutMe": "", "groups": [], "user_permissions": []}}, {"model": "authapp.user", "pk": 22, "fields": {"password": "pbkdf2_sha256$216000$TzUnjOOHEJyu$VeXDR0PiTvTfpn+22/vXiUE2u5JYPx7jjYuxoUyYmfc=", "last_login": null, "is_superuser": false, "first_name": "", "last_name": "", "is_staff": false, "is_active": false, "date_joined": "2021-02-14T03:12:42.853Z", "username": "user9", "name": "Саша", "surname": "Пушкин", "status_block": false, "status_update": "2021-02-14T03:12:42.853Z", "date_create": "2021-02-14T03:12:42.853Z", "date_update": "2021-02-14T03:12:42.853Z", "email": "tcilop-p2@yandex.ru", "avatar": "", "age": 0, "aboutMe": "", "groups": [1], "user_permissions": []}}, {"model": "authapp.user", "pk": 23, "fields": {"password": "pbkdf2_sha256$216000$udd1j1jskDsk$/L+XQ7q2uuYQuAQ2qGpGrNLB0gmf7HzwF9BPk5flwG0=", "last_login": null, "is_superuser": false, "first_name": "", "last_name": "", "is_staff": false, "is_active": true, "date_joined": "2021-02-14T03:16:03.813Z", "username": "user10", "name": "Саша", "surname": "Пушкин", "status_block": false, "status_update": "2021-02-14T03:16:03.813Z", "date_create": "2021-02-14T03:16:03.813Z", "date_update": "2021-02-14T03:16:03.813Z", "email": "tcilop-p3@yandex.ru", "avatar": "", "age": 0, "aboutMe": "", "groups": [], "user_permissions": []}}, {"model": "authapp.user", "pk": 24, "fields": {"password": "pbkdf2_sha256$216000$Hmj3VnRmgcoi$KnJAjT9iUvCfm5ZchSRW/Qr4skRgsWEa34rYz/+TqYE=", "last_login": "2021-02-27T02:43:45.346Z", "is_superuser": false, "first_name": "", "last_name": "", "is_staff": false, "is_active": true, "date_joined": "2021-02-14T21:24:38.375Z", "username": "user666", "name": "Мефодий Исаевич", "surname": "Тоффель", "status_block": false, "status_update": "2021-02-14T21:24:38.375Z", "date_create": "2021-02-14T21:24:38.375Z", "date_update": "2021-02-14T21:24:38.375Z", "email": "kirikeza@mail.ru", "avatar": "users_avatars/mefisto.png", "age": 3605, "aboutMe": "Я — часть той силы, что вечно хочет зла и вечно совершает благо.", "groups": [1], "user_permissions": []}}, {"model": "authapp.user", "pk": 25, "fields": {"password": "pbkdf2_sha256$216000$k576a4htYU8B$Sikd2Bgcat9khvuvRfs5neE+poTdsAARW+Wngj3lD5o=", "last_login": "2021-02-23T03:18:05.592Z", "is_superuser": false, "first_name": "", "last_name": "", "is_staff": false, "is_active": true, "date_joined": "2021-02-15T03:35:18.536Z", "username": "pushkin", "name": "Александр", "surname": "Пушкин", "status_block": false, "status_update": "2021-02-15T03:35:18.536Z", "date_create": "2021-02-15T03:35:18.536Z", "date_update": "2021-02-15T03:35:18.536Z", "email": "tcilop-p@yandex.ru", "avatar": "users_avatars/pushkin.jpeg", "age": 221, "aboutMe": "Характер нордический, стойкий", "groups": [], "user_permissions": []}}, {"model": "authapp.user", "pk": 26, "fields": {"password": "pbkdf2_sha256$216000$hGevogexxkVD$BhP2d3pBH/OtXHIjvUDxmUpPyM3vMOyKTWGk/rP8K9Q=", "last_login": "2021-02-16T17:22:55.588Z", "is_superuser": false, "first_name": "", "last_name": "", "is_staff": false, "is_active": true, "date_joined": "2021-02-16T17:22:53.339Z", "username": "qwerty", "name": "qwerty", "surname": "qwerty", "status_block": false, "status_update": "2021-02-16T17:22:53.339Z", "date_create": "2021-02-16T17:22:53.339Z", "date_update": "2021-02-16T17:22:53.339Z", "email": "1@d.ru", "avatar": "", "age": 0, "aboutMe": "", "groups": [], "user_permissions": []}}, {"model": "authapp.user", "pk": 27, "fields": {"password": "pbkdf2_sha256$216000$ugRnmR5xTWmo$JRweyHLaZR9mihBWHIv9JKZRtf/kcjGp3PHtKKxj6o0=", "last_login": "2021-02-26T16:42:01.823Z", "is_superuser": false, "first_name": "", "last_name": "", "is_staff": false, "is_active": true, "date_joined": "2021-02-16T17:25:22.304Z", "username": "qwerty1", "name": "qwerty1", "surname": "qwerty1", "status_block": false, "status_update": "2021-02-16T17:25:22.304Z", "date_create": "2021-02-16T17:25:22.304Z", "date_update": "2021-02-16T17:25:22.304Z", "email": "nuinurrr@yandex.ru", "avatar": "", "age": 0, "aboutMe": "", "groups": [], "user_permissions": []}}, {"model": "authapp.user", "pk": 28, "fields": {"password": "pbkdf2_sha256$216000$tCP6MdAD18Qp$iAR16i548zK0q1nVIx2eex/ej7ZCamVkbDcHCXb8REg=", "last_login": null, "is_superuser": false, "first_name": "", "last_name": "", "is_staff": false, "is_active": true, "date_joined": "2021-02-18T14:41:15.028Z", "username": "user669", "name": "Николай", "surname": "Романов", "status_block": false, "status_update": "2021-02-18T14:41:15.028Z", "date_create": "2021-02-18T14:41:15.028Z", "date_update": "2021-02-18T14:41:15.028Z", "email": "dewopa8463@mayhco.com", "avatar": "", "age": 0, "aboutMe": "", "groups": [], "user_permissions": []}}, {"model": "authapp.user", "pk": 29, "fields": {"password": "pbkdf2_sha256$216000$TAN0m2pXq3ck$SdDl0sC/E+V3w6CtHJYvBnT0Ee8KI9Aw414YVGrOrFQ=", "last_login": null, "is_superuser": false, "first_name": "", "last_name": "", "is_staff": false, "is_active": true, "date_joined": "2021-02-19T03:13:51.369Z", "username": "user9012", "name": "Джон", "surname": "Миллер", "status_block": false, "status_update": "2021-02-19T03:13:51.369Z", "date_create": "2021-02-19T03:13:51.369Z", "date_update": "2021-02-19T03:13:51.369Z", "email": "jagomeb829@iconmle.com", "avatar": "", "age": 0, "aboutMe": "", "groups": [], "user_permissions": []}}, {"model": "authapp.user", "pk": 30, "fields": {"password": "pbkdf2_sha256$216000$xxc1SbL6bDNg$GM9UnXXx9nuS7V2YqrNzmf12EBJBJdKv0RAj2/J1Lcs=", "last_login": null, "is_superuser": false, "first_name": "", "last_name": "", "is_staff": false, "is_active": false, "date_joined": "2021-02-19T03:21:37.612Z", "username": "user90123", "name": "Джон", "surname": "Миллер", "status_block": false, "status_update": "2021-02-19T03:21:37.612Z", "date_create": "2021-02-19T03:21:37.612Z", "date_update": "2021-02-19T03:21:37.612Z", "email": "jagomeb828@iconmle.com", "avatar": "", "age": 0, "aboutMe": "", "groups": [], "user_permissions": []}}, {"model": "authapp.user", "pk": 31, "fields": {"password": "pbkdf2_sha256$216000$FMv60MIcMuA7$VkLokY+e5acKxmyFIltduGnOwI9OIZyIZwdnCicu0vY=", "last_login": null, "is_superuser": false, "first_name": "", "last_name": "", "is_staff": false, "is_active": false, "date_joined": "2021-02-19T03:29:48.874Z", "username": "user90124", "name": "Джон", "surname": "Миллер", "status_block": false, "status_update": "2021-02-19T03:29:48.874Z", "date_create": "2021-02-19T03:29:48.874Z", "date_update": "2021-02-19T03:29:48.874Z", "email": "jagomeb88@iconmle.com", "avatar": "", "age": 0, "aboutMe": "", "groups": [], "user_permissions": []}}, {"model": "authapp.user", "pk": 32, "fields": {"password": "pbkdf2_sha256$216000$hjgFsQOt9wba$WaSRlU8xgHZ3oSmzvuHtj1YTYbAXLb69I+bLOpEIyWA=", "last_login": null, "is_superuser": false, "first_name": "", "last_name": "", "is_staff": false, "is_active": false, "date_joined": "2021-02-19T03:32:38.240Z", "username": "user901245", "name": "Джон", "surname": "Миллер", "status_block": false, "status_update": "2021-02-19T03:32:38.240Z", "date_create": "2021-02-19T03:32:38.240Z", "date_update": "2021-02-19T03:32:38.240Z", "email": "jagomebe8@iconmle.com", "avatar": "", "age": 0, "aboutMe": "", "groups": [], "user_permissions": []}}, {"model": "authapp.user", "pk": 33, "fields": {"password": "pbkdf2_sha256$216000$qQTf6OoYFi6e$pfURj+ZDMLBTUKDe/Wve3wwjaJhiLDds0XceInmCe4A=", "last_login": null, "is_superuser": false, "first_name": "", "last_name": "", "is_staff": false, "is_active": false, "date_joined": "2021-02-19T03:36:46.823Z", "username": "user9012434", "name": "Джон", "surname": "Миллер", "status_block": false, "status_update": "2021-02-19T03:36:46.823Z", "date_create": "2021-02-19T03:36:46.823Z", "date_update": "2021-02-19T03:36:46.823Z", "email": "jagsomebe8@iconmle.com", "avatar": "", "age": 0, "aboutMe": "", "groups": [], "user_permissions": []}}, {"model": "authapp.user", "pk": 34, "fields": {"password": "pbkdf2_sha256$216000$rgj4LXxuyq1s$G648+wZDX1GWnkx5FXhwx73IKr9JwxaGjU6Mi8uGWjk=", "last_login": null, "is_superuser": false, "first_name": "", "last_name": "", "is_staff": false, "is_active": false, "date_joined": "2021-02-19T03:37:35.616Z", "username": "user90124334", "name": "Джон", "surname": "Миллер", "status_block": false, "status_update": "2021-02-19T03:37:35.616Z", "date_create": "2021-02-19T03:37:35.616Z", "date_update": "2021-02-19T03:37:35.616Z", "email": "jagsomeddbe8@iconmle.com", "avatar": "", "age": 0, "aboutMe": "", "groups": [], "user_permissions": []}}, {"model": "authapp.user", "pk": 35, "fields": {"password": "pbkdf2_sha256$216000$NfrzUUpDXpxU$afagh2P3ZI6mEvkN1QOTxytv+8r8IB37RQ0pwIiF7YE=", "last_login": null, "is_superuser": false, "first_name": "", "last_name": "", "is_staff": false, "is_active": false, "date_joined": "2021-02-19T03:42:58.914Z", "username": "user901243344", "name": "Джон", "surname": "Миллер", "status_block": false, "status_update": "2021-02-19T03:42:58.914Z", "date_create": "2021-02-19T03:42:58.914Z", "date_update": "2021-02-19T03:42:58.914Z", "email": "jagsomedsdbe8@iconmle.com", "avatar": "", "age": 0, "aboutMe": "", "groups": [], "user_permissions": []}}, {"model": "authapp.user", "pk": 36, "fields": {"password": "pbkdf2_sha256$216000$lLajOY37XRw0$EfjL3hWCtT9ALHrdCeOtWLe/zteGnOqHQXxhkimiZy4=", "last_login": "2021-02-19T17:40:55.620Z", "is_superuser": false, "first_name": "", "last_name": "", "is_staff": false, "is_active": true, "date_joined": "2021-02-19T17:39:34.247Z", "username": "user987", "name": "Степан", "surname": "Степанов", "status_block": false, "status_update": "2021-02-19T17:39:34.247Z", "date_create": "2021-02-19T17:39:34.247Z", "date_update": "2021-02-19T17:39:34.247Z", "email": "jadeg18334@iconmle.com", "avatar": "", "age": 0, "aboutMe": "", "groups": [], "user_permissions": []}}, {"model": "authapp.user", "pk": 37, "fields": {"password": "pbkdf2_sha256$216000$9FWR2KR5tIA6$4jBPFPNSYpFi8TK6507jnRfHgqvLCAYlzPCAUIiQLDo=", "last_login": null, "is_superuser": false, "first_name": "", "last_name": "", "is_staff": false, "is_active": true, "date_joined": "2021-02-20T03:37:53.348Z", "username": "user172", "name": "Степан", "surname": "Степанов", "status_block": false, "status_update": "2021-02-20T03:37:53.348Z", "date_create": "2021-02-20T03:37:53.348Z", "date_update": "2021-02-20T03:37:53.348Z", "email": "poviba7998@dxecig.com", "avatar": "", "age": 0, "aboutMe": "", "groups": [], "user_permissions": []}}, {"model": "authapp.user", "pk": 38, "fields": {"password": "pbkdf2_sha256$216000$EKpWk6D4U0GN$iyDFt8JGrRZ35aPBRZImlxnS1u0G+Scy+JfiSByKhoU=", "last_login": "2021-02-22T07:13:51.288Z", "is_superuser": false, "first_name": "", "last_name": "", "is_staff": false, "is_active": true, "date_joined": "2021-02-22T07:11:39.061Z", "username": "A0981261272", "name": "Al", "surname": "Kir", "status_block": false, "status_update": "2021-02-22T07:11:39.061Z", "date_create": "2021-02-22T07:11:39.061Z", "date_update": "2021-02-22T07:11:39.061Z", "email": "avladimkir@gmail.com", "avatar": "", "age": 0, "aboutMe": "", "groups": [], "user_permissions": []}}, {"model": "authapp.user", "pk": 39, "fields": {"password": "pbkdf2_sha256$216000$6UvLjxHisL57$pPcnqlskqUSFMyydVoeJx2lZG2wBQHqh8rnKL7Feep8=", "last_login": "2021-02-23T05:03:00.751Z", "is_superuser": false, "first_name": "", "last_name": "", "is_staff": false, "is_active": true, "date_joined": "2021-02-23T03:03:33.623Z", "username": "amazon", "name": "Амазон", "surname": "Волгин", "status_block": false, "status_update": "2021-02-23T03:03:33.623Z", "date_create": "2021-02-23T03:03:33.623Z", "date_update": "2021-02-23T03:03:33.623Z", "email": "hajewev625@geeky83.com", "avatar": "", "age": 0, "aboutMe": "", "groups": [], "user_permissions": []}}, {"model": "authapp.user", "pk": 40, "fields": {"password": "pbkdf2_sha256$216000$FtMCwVdToFpi$OPrs+jh2PAw1EYnHf7SoUd+ZY8CyXIV799CDylLLvkM=", "last_login": "2021-02-23T03:21:35.842Z", "is_superuser": false, "first_name": "", "last_name": "", "is_staff": false, "is_active": true, "date_joined": "2021-02-23T03:20:54.055Z", "username": "schwarz", "name": "Arnold", "surname": "Schwarzenegger", "status_block": false, "status_update": "2021-02-23T03:20:54.056Z", "date_create": "2021-02-23T03:20:54.056Z", "date_update": "2021-02-23T03:20:54.056Z", "email": "rawev45514@dxecig.com", "avatar": "", "age": 0, "aboutMe": "", "groups": [], "user_permissions": []}}, {"model": "authapp.user", "pk": 41, "fields": {"password": "pbkdf2_sha256$216000$IFFHApqLnXYg$SF6mSn7V8ZbeTQGWPodREuhYbut/0N7OgNFf33XA+k4=", "last_login": null, "is_superuser": false, "first_name": "", "last_name": "", "is_staff": false, "is_active": true, "date_joined": "2021-02-25T16:07:43.991Z", "username": "reanimator23", "name": "Mikhail", "surname": "Ageev", "status_block": false, "status_update": "2021-02-25T14:07:43.991Z", "date_create": "2021-02-25T14:07:43.991Z", "date_update": "2021-02-25T14:07:43.991Z", "email": "Reanimator23@bk.ru", "avatar": "", "age": 0, "aboutMe": "", "groups": [], "user_permissions": []}}, {"model": "authapp.user", "pk": 42, "fields": {"password": "pbkdf2_sha256$216000$xpUbbrB6Zogh$3KxEMit1km60WlfXZTIb3IFyxmaSCKlXCzmWbUnMJ8A=", "last_login": "2021-02-27T06:53:23.106Z", "is_superuser": false, "first_name": "", "last_name": "", "is_staff": false, "is_active": true, "date_joined": "2021-02-27T06:52:52.857Z", "username": "albus", "name": "Albus", "surname": "Dumbledore", "status_block": false, "status_update": "2021-02-27T06:52:52.857Z", "date_create": "2021-02-27T06:52:52.857Z", "date_update": "2021-02-27T06:52:52.857Z", "email": "oleg.gnome@gmail.com", "avatar": "users_avatars/XeHUjqmN_400x400.jpg", "age": 30, "aboutMe": "Albus Dumbledore was never proud or vain; he could find something to value in anyone, however apparently insignificant or wretched, and I believe that his early losses endowed him with great humanity and sympathy. I shall miss his friendship more than I can say, but my loss is as nothing compared to the Wizarding world’s. That he was the most inspiring and the best loved of all Hogwarts headmasters cannot be in question. He died as he lived: working always for the greater good and, to his last hour, as will", "groups": [], "user_permissions": []}}]